{
    "$schema": "http://adaptivecards.io/schemas/adaptive-card.json",
    "version": "1.3",
    "type": "AdaptiveCard",
    "body": [
        {
            "type": "TextBlock",
            "text": "Welcome to the Self Service Bot",
            "size": "large",
            "weight": "bolder",
            "isSubtle": false
        },
        {
            "type": "TextBlock",
            "text": "For a list of possible actions click the button below",
            "size": "small"
        }
    ],
    "actions": [
        {
          "type": "Action.Submit",
          "title": "List Actions",
          "data": "help"
        }
    ]
}